proxycalc/__init__.py
proxycalc-0.1.4.dist-info/LICENSE
proxycalc-0.1.4.dist-info/WHEEL
proxycalc-0.1.4.dist-info/METADATA
proxycalc-0.1.4.dist-info/RECORD
