Metadata-Version: 2.1
Name: proxycalc
Version: 0.1.4
Summary: Proxycalc provides a Calculator class for handling basic mathematical
Author-email: Ebube Okoli <ebubeokoli@rocketmail.com>
Requires-Python: >=3.7
Classifier: License :: OSI Approved :: MIT License
Project-URL: Home, https://github.com/leonardokhorliey/proxycalc
